<annotation>
	<folder></folder>
	<filename>000783_jpg.rf.795be18aa0d1f6d01a0867c87ebdb8c0.jpg</filename>
	<path>000783_jpg.rf.795be18aa0d1f6d01a0867c87ebdb8c0.jpg</path>
	<source>
		<database>roboflow.ai</database>
	</source>
	<size>
		<width>640</width>
		<height>640</height>
		<depth>3</depth>
	</size>
	<segmented>0</segmented>
	<object>
		<name>head</name>
		<pose>Unspecified</pose>
		<truncated>0</truncated>
		<difficult>0</difficult>
		<occluded>0</occluded>
		<bndbox>
			<xmin>533</xmin>
			<xmax>613</xmax>
			<ymin>93</ymin>
			<ymax>235</ymax>
		</bndbox>
	</object>
	<object>
		<name>head</name>
		<pose>Unspecified</pose>
		<truncated>0</truncated>
		<difficult>0</difficult>
		<occluded>0</occluded>
		<bndbox>
			<xmin>280</xmin>
			<xmax>331</xmax>
			<ymin>130</ymin>
			<ymax>222</ymax>
		</bndbox>
	</object>
	<object>
		<name>head</name>
		<pose>Unspecified</pose>
		<truncated>0</truncated>
		<difficult>0</difficult>
		<occluded>0</occluded>
		<bndbox>
			<xmin>457</xmin>
			<xmax>508</xmax>
			<ymin>137</ymin>
			<ymax>239</ymax>
		</bndbox>
	</object>
	<object>
		<name>head</name>
		<pose>Unspecified</pose>
		<truncated>0</truncated>
		<difficult>0</difficult>
		<occluded>0</occluded>
		<bndbox>
			<xmin>426</xmin>
			<xmax>460</xmax>
			<ymin>152</ymin>
			<ymax>227</ymax>
		</bndbox>
	</object>
	<object>
		<name>head</name>
		<pose>Unspecified</pose>
		<truncated>0</truncated>
		<difficult>0</difficult>
		<occluded>0</occluded>
		<bndbox>
			<xmin>120</xmin>
			<xmax>192</xmax>
			<ymin>141</ymin>
			<ymax>275</ymax>
		</bndbox>
	</object>
	<object>
		<name>person</name>
		<pose>Unspecified</pose>
		<truncated>0</truncated>
		<difficult>0</difficult>
		<occluded>0</occluded>
		<bndbox>
			<xmin>395</xmin>
			<xmax>456</xmax>
			<ymin>137</ymin>
			<ymax>538</ymax>
		</bndbox>
	</object>
	<object>
		<name>person</name>
		<pose>Unspecified</pose>
		<truncated>0</truncated>
		<difficult>0</difficult>
		<occluded>0</occluded>
		<bndbox>
			<xmin>507</xmin>
			<xmax>636</xmax>
			<ymin>96</ymin>
			<ymax>630</ymax>
		</bndbox>
	</object>
	<object>
		<name>person</name>
		<pose>Unspecified</pose>
		<truncated>0</truncated>
		<difficult>0</difficult>
		<occluded>0</occluded>
		<bndbox>
			<xmin>239</xmin>
			<xmax>381</xmax>
			<ymin>128</ymin>
			<ymax>632</ymax>
		</bndbox>
	</object>
	<object>
		<name>person</name>
		<pose>Unspecified</pose>
		<truncated>0</truncated>
		<difficult>0</difficult>
		<occluded>0</occluded>
		<bndbox>
			<xmin>72</xmin>
			<xmax>224</xmax>
			<ymin>127</ymin>
			<ymax>640</ymax>
		</bndbox>
	</object>
	<object>
		<name>person</name>
		<pose>Unspecified</pose>
		<truncated>0</truncated>
		<difficult>0</difficult>
		<occluded>0</occluded>
		<bndbox>
			<xmin>443</xmin>
			<xmax>532</xmax>
			<ymin>133</ymin>
			<ymax>640</ymax>
		</bndbox>
	</object>
</annotation>
