<annotation>
	<folder></folder>
	<filename>gettyimages-184334080-612x612_jpg.rf.894d472c71200a3bdd09618e61c331ab.jpg</filename>
	<path>gettyimages-184334080-612x612_jpg.rf.894d472c71200a3bdd09618e61c331ab.jpg</path>
	<source>
		<database>roboflow.ai</database>
	</source>
	<size>
		<width>640</width>
		<height>640</height>
		<depth>3</depth>
	</size>
	<segmented>0</segmented>
	<object>
		<name>white</name>
		<pose>Unspecified</pose>
		<truncated>0</truncated>
		<difficult>0</difficult>
		<occluded>0</occluded>
		<bndbox>
			<xmin>211</xmin>
			<xmax>307</xmax>
			<ymin>124</ymin>
			<ymax>232</ymax>
		</bndbox>
	</object>
	<object>
		<name>glass</name>
		<pose>Unspecified</pose>
		<truncated>0</truncated>
		<difficult>0</difficult>
		<occluded>0</occluded>
		<bndbox>
			<xmin>344</xmin>
			<xmax>418</xmax>
			<ymin>166</ymin>
			<ymax>218</ymax>
		</bndbox>
	</object>
	<object>
		<name>glass</name>
		<pose>Unspecified</pose>
		<truncated>0</truncated>
		<difficult>0</difficult>
		<occluded>0</occluded>
		<bndbox>
			<xmin>215</xmin>
			<xmax>296</xmax>
			<ymin>195</ymin>
			<ymax>250</ymax>
		</bndbox>
	</object>
	<object>
		<name>person</name>
		<pose>Unspecified</pose>
		<truncated>0</truncated>
		<difficult>0</difficult>
		<occluded>0</occluded>
		<bndbox>
			<xmin>322</xmin>
			<xmax>598</xmax>
			<ymin>98</ymin>
			<ymax>638</ymax>
		</bndbox>
	</object>
	<object>
		<name>person</name>
		<pose>Unspecified</pose>
		<truncated>0</truncated>
		<difficult>0</difficult>
		<occluded>0</occluded>
		<bndbox>
			<xmin>117</xmin>
			<xmax>346</xmax>
			<ymin>106</ymin>
			<ymax>632</ymax>
		</bndbox>
	</object>
	<object>
		<name>white</name>
		<pose>Unspecified</pose>
		<truncated>0</truncated>
		<difficult>0</difficult>
		<occluded>0</occluded>
		<bndbox>
			<xmin>342</xmin>
			<xmax>434</xmax>
			<ymin>112</ymin>
			<ymax>196</ymax>
		</bndbox>
	</object>
</annotation>
