<annotation>
	<folder></folder>
	<filename>gettyimages-1139562244-612x612_jpg.rf.e1da4a5ab74bf2263fc74cdcaadd82b1.jpg</filename>
	<path>gettyimages-1139562244-612x612_jpg.rf.e1da4a5ab74bf2263fc74cdcaadd82b1.jpg</path>
	<source>
		<database>roboflow.ai</database>
	</source>
	<size>
		<width>640</width>
		<height>640</height>
		<depth>3</depth>
	</size>
	<segmented>0</segmented>
	<object>
		<name>white</name>
		<pose>Unspecified</pose>
		<truncated>0</truncated>
		<difficult>0</difficult>
		<occluded>0</occluded>
		<bndbox>
			<xmin>238</xmin>
			<xmax>378</xmax>
			<ymin>86</ymin>
			<ymax>229</ymax>
		</bndbox>
	</object>
	<object>
		<name>glass</name>
		<pose>Unspecified</pose>
		<truncated>0</truncated>
		<difficult>0</difficult>
		<occluded>0</occluded>
		<bndbox>
			<xmin>258</xmin>
			<xmax>339</xmax>
			<ymin>210</ymin>
			<ymax>270</ymax>
		</bndbox>
	</object>
	<object>
		<name>person</name>
		<pose>Unspecified</pose>
		<truncated>0</truncated>
		<difficult>0</difficult>
		<occluded>0</occluded>
		<bndbox>
			<xmin>195</xmin>
			<xmax>444</xmax>
			<ymin>79</ymin>
			<ymax>635</ymax>
		</bndbox>
	</object>
	<object>
		<name>vest</name>
		<pose>Unspecified</pose>
		<truncated>0</truncated>
		<difficult>0</difficult>
		<occluded>0</occluded>
		<bndbox>
			<xmin>210</xmin>
			<xmax>427</xmax>
			<ymin>327</ymin>
			<ymax>640</ymax>
		</bndbox>
	</object>
</annotation>
