<annotation>
	<folder></folder>
	<filename>ppe_0074_jpg.rf.6d2e710fd6212c8f7219c9888528cd20.jpg</filename>
	<path>ppe_0074_jpg.rf.6d2e710fd6212c8f7219c9888528cd20.jpg</path>
	<source>
		<database>roboflow.ai</database>
	</source>
	<size>
		<width>640</width>
		<height>640</height>
		<depth>3</depth>
	</size>
	<segmented>0</segmented>
	<object>
		<name>red</name>
		<pose>Unspecified</pose>
		<truncated>0</truncated>
		<difficult>0</difficult>
		<occluded>0</occluded>
		<bndbox>
			<xmin>197</xmin>
			<xmax>285</xmax>
			<ymin>330</ymin>
			<ymax>428</ymax>
		</bndbox>
	</object>
	<object>
		<name>yellow</name>
		<pose>Unspecified</pose>
		<truncated>0</truncated>
		<difficult>0</difficult>
		<occluded>0</occluded>
		<bndbox>
			<xmin>73</xmin>
			<xmax>93</xmax>
			<ymin>99</ymin>
			<ymax>126</ymax>
		</bndbox>
	</object>
	<object>
		<name>yellow</name>
		<pose>Unspecified</pose>
		<truncated>0</truncated>
		<difficult>0</difficult>
		<occluded>0</occluded>
		<bndbox>
			<xmin>350</xmin>
			<xmax>368</xmax>
			<ymin>176</ymin>
			<ymax>199</ymax>
		</bndbox>
	</object>
	<object>
		<name>person</name>
		<pose>Unspecified</pose>
		<truncated>0</truncated>
		<difficult>0</difficult>
		<occluded>0</occluded>
		<bndbox>
			<xmin>156</xmin>
			<xmax>359</xmax>
			<ymin>327</ymin>
			<ymax>601</ymax>
		</bndbox>
	</object>
	<object>
		<name>person</name>
		<pose>Unspecified</pose>
		<truncated>0</truncated>
		<difficult>0</difficult>
		<occluded>0</occluded>
		<bndbox>
			<xmin>56</xmin>
			<xmax>101</xmax>
			<ymin>91</ymin>
			<ymax>242</ymax>
		</bndbox>
	</object>
	<object>
		<name>person</name>
		<pose>Unspecified</pose>
		<truncated>0</truncated>
		<difficult>0</difficult>
		<occluded>0</occluded>
		<bndbox>
			<xmin>341</xmin>
			<xmax>384</xmax>
			<ymin>170</ymin>
			<ymax>255</ymax>
		</bndbox>
	</object>
</annotation>
