<annotation>
	<folder></folder>
	<filename>ppe_0189_jpg.rf.7a3fe817de788a7304dc7bff77584181.jpg</filename>
	<path>ppe_0189_jpg.rf.7a3fe817de788a7304dc7bff77584181.jpg</path>
	<source>
		<database>roboflow.ai</database>
	</source>
	<size>
		<width>640</width>
		<height>640</height>
		<depth>3</depth>
	</size>
	<segmented>0</segmented>
	<object>
		<name>white</name>
		<pose>Unspecified</pose>
		<truncated>0</truncated>
		<difficult>0</difficult>
		<occluded>0</occluded>
		<bndbox>
			<xmin>234</xmin>
			<xmax>500</xmax>
			<ymin>20</ymin>
			<ymax>286</ymax>
		</bndbox>
	</object>
	<object>
		<name>person</name>
		<pose>Unspecified</pose>
		<truncated>0</truncated>
		<difficult>0</difficult>
		<occluded>0</occluded>
		<bndbox>
			<xmin>173</xmin>
			<xmax>549</xmax>
			<ymin>20</ymin>
			<ymax>630</ymax>
		</bndbox>
	</object>
</annotation>
