<annotation>
	<folder></folder>
	<filename>ppe_1100_jpg.rf.f355ffc83cc1f1afd6ec71440fe05ef6.jpg</filename>
	<path>ppe_1100_jpg.rf.f355ffc83cc1f1afd6ec71440fe05ef6.jpg</path>
	<source>
		<database>roboflow.ai</database>
	</source>
	<size>
		<width>640</width>
		<height>640</height>
		<depth>3</depth>
	</size>
	<segmented>0</segmented>
	<object>
		<name>person</name>
		<pose>Unspecified</pose>
		<truncated>0</truncated>
		<difficult>0</difficult>
		<occluded>0</occluded>
		<bndbox>
			<xmin>179</xmin>
			<xmax>214</xmax>
			<ymin>463</ymin>
			<ymax>492</ymax>
		</bndbox>
	</object>
	<object>
		<name>yellow</name>
		<pose>Unspecified</pose>
		<truncated>0</truncated>
		<difficult>0</difficult>
		<occluded>0</occluded>
		<bndbox>
			<xmin>364</xmin>
			<xmax>373</xmax>
			<ymin>123</ymin>
			<ymax>134</ymax>
		</bndbox>
	</object>
	<object>
		<name>person</name>
		<pose>Unspecified</pose>
		<truncated>0</truncated>
		<difficult>0</difficult>
		<occluded>0</occluded>
		<bndbox>
			<xmin>451</xmin>
			<xmax>472</xmax>
			<ymin>119</ymin>
			<ymax>175</ymax>
		</bndbox>
	</object>
	<object>
		<name>person</name>
		<pose>Unspecified</pose>
		<truncated>0</truncated>
		<difficult>0</difficult>
		<occluded>0</occluded>
		<bndbox>
			<xmin>359</xmin>
			<xmax>378</xmax>
			<ymin>122</ymin>
			<ymax>161</ymax>
		</bndbox>
	</object>
	<object>
		<name>person</name>
		<pose>Unspecified</pose>
		<truncated>0</truncated>
		<difficult>0</difficult>
		<occluded>0</occluded>
		<bndbox>
			<xmin>328</xmin>
			<xmax>346</xmax>
			<ymin>140</ymin>
			<ymax>165</ymax>
		</bndbox>
	</object>
	<object>
		<name>person</name>
		<pose>Unspecified</pose>
		<truncated>0</truncated>
		<difficult>0</difficult>
		<occluded>0</occluded>
		<bndbox>
			<xmin>487</xmin>
			<xmax>517</xmax>
			<ymin>44</ymin>
			<ymax>94</ymax>
		</bndbox>
	</object>
	<object>
		<name>person</name>
		<pose>Unspecified</pose>
		<truncated>0</truncated>
		<difficult>0</difficult>
		<occluded>0</occluded>
		<bndbox>
			<xmin>191</xmin>
			<xmax>206</xmax>
			<ymin>100</ymin>
			<ymax>133</ymax>
		</bndbox>
	</object>
	<object>
		<name>person</name>
		<pose>Unspecified</pose>
		<truncated>0</truncated>
		<difficult>0</difficult>
		<occluded>0</occluded>
		<bndbox>
			<xmin>216</xmin>
			<xmax>227</xmax>
			<ymin>99</ymin>
			<ymax>140</ymax>
		</bndbox>
	</object>
</annotation>
