<annotation>
	<folder></folder>
	<filename>ppe_1152_jpg.rf.4b30b5ffc29008068a7722f49b859956.jpg</filename>
	<path>ppe_1152_jpg.rf.4b30b5ffc29008068a7722f49b859956.jpg</path>
	<source>
		<database>roboflow.ai</database>
	</source>
	<size>
		<width>640</width>
		<height>640</height>
		<depth>3</depth>
	</size>
	<segmented>0</segmented>
	<object>
		<name>blue</name>
		<pose>Unspecified</pose>
		<truncated>0</truncated>
		<difficult>0</difficult>
		<occluded>0</occluded>
		<bndbox>
			<xmin>125</xmin>
			<xmax>169</xmax>
			<ymin>409</ymin>
			<ymax>474</ymax>
		</bndbox>
	</object>
	<object>
		<name>blue</name>
		<pose>Unspecified</pose>
		<truncated>0</truncated>
		<difficult>0</difficult>
		<occluded>0</occluded>
		<bndbox>
			<xmin>281</xmin>
			<xmax>308</xmax>
			<ymin>374</ymin>
			<ymax>421</ymax>
		</bndbox>
	</object>
	<object>
		<name>person</name>
		<pose>Unspecified</pose>
		<truncated>0</truncated>
		<difficult>0</difficult>
		<occluded>0</occluded>
		<bndbox>
			<xmin>102</xmin>
			<xmax>190</xmax>
			<ymin>399</ymin>
			<ymax>640</ymax>
		</bndbox>
	</object>
	<object>
		<name>person</name>
		<pose>Unspecified</pose>
		<truncated>0</truncated>
		<difficult>0</difficult>
		<occluded>0</occluded>
		<bndbox>
			<xmin>276</xmin>
			<xmax>341</xmax>
			<ymin>381</ymin>
			<ymax>632</ymax>
		</bndbox>
	</object>
	<object>
		<name>person</name>
		<pose>Unspecified</pose>
		<truncated>0</truncated>
		<difficult>0</difficult>
		<occluded>0</occluded>
		<bndbox>
			<xmin>249</xmin>
			<xmax>298</xmax>
			<ymin>365</ymin>
			<ymax>623</ymax>
		</bndbox>
	</object>
</annotation>
