<annotation>
	<folder></folder>
	<filename>ppe_0959_jpg.rf.f3cce227600c7d55a6f9a6c45e8e1c2f.jpg</filename>
	<path>ppe_0959_jpg.rf.f3cce227600c7d55a6f9a6c45e8e1c2f.jpg</path>
	<source>
		<database>roboflow.ai</database>
	</source>
	<size>
		<width>640</width>
		<height>640</height>
		<depth>3</depth>
	</size>
	<segmented>0</segmented>
	<object>
		<name>white</name>
		<pose>Unspecified</pose>
		<truncated>0</truncated>
		<difficult>0</difficult>
		<occluded>0</occluded>
		<bndbox>
			<xmin>144</xmin>
			<xmax>184</xmax>
			<ymin>184</ymin>
			<ymax>225</ymax>
		</bndbox>
	</object>
	<object>
		<name>white</name>
		<pose>Unspecified</pose>
		<truncated>0</truncated>
		<difficult>0</difficult>
		<occluded>0</occluded>
		<bndbox>
			<xmin>355</xmin>
			<xmax>401</xmax>
			<ymin>197</ymin>
			<ymax>236</ymax>
		</bndbox>
	</object>
	<object>
		<name>white</name>
		<pose>Unspecified</pose>
		<truncated>0</truncated>
		<difficult>0</difficult>
		<occluded>0</occluded>
		<bndbox>
			<xmin>262</xmin>
			<xmax>302</xmax>
			<ymin>195</ymin>
			<ymax>247</ymax>
		</bndbox>
	</object>
	<object>
		<name>white</name>
		<pose>Unspecified</pose>
		<truncated>0</truncated>
		<difficult>0</difficult>
		<occluded>0</occluded>
		<bndbox>
			<xmin>23</xmin>
			<xmax>59</xmax>
			<ymin>205</ymin>
			<ymax>239</ymax>
		</bndbox>
	</object>
	<object>
		<name>white</name>
		<pose>Unspecified</pose>
		<truncated>0</truncated>
		<difficult>0</difficult>
		<occluded>0</occluded>
		<bndbox>
			<xmin>444</xmin>
			<xmax>516</xmax>
			<ymin>203</ymin>
			<ymax>262</ymax>
		</bndbox>
	</object>
	<object>
		<name>white</name>
		<pose>Unspecified</pose>
		<truncated>0</truncated>
		<difficult>0</difficult>
		<occluded>0</occluded>
		<bndbox>
			<xmin>184</xmin>
			<xmax>254</xmax>
			<ymin>225</ymin>
			<ymax>294</ymax>
		</bndbox>
	</object>
	<object>
		<name>person</name>
		<pose>Unspecified</pose>
		<truncated>0</truncated>
		<difficult>0</difficult>
		<occluded>0</occluded>
		<bndbox>
			<xmin>11</xmin>
			<xmax>84</xmax>
			<ymin>190</ymin>
			<ymax>473</ymax>
		</bndbox>
	</object>
	<object>
		<name>person</name>
		<pose>Unspecified</pose>
		<truncated>0</truncated>
		<difficult>0</difficult>
		<occluded>0</occluded>
		<bndbox>
			<xmin>115</xmin>
			<xmax>208</xmax>
			<ymin>165</ymin>
			<ymax>520</ymax>
		</bndbox>
	</object>
	<object>
		<name>person</name>
		<pose>Unspecified</pose>
		<truncated>0</truncated>
		<difficult>0</difficult>
		<occluded>0</occluded>
		<bndbox>
			<xmin>237</xmin>
			<xmax>328</xmax>
			<ymin>188</ymin>
			<ymax>563</ymax>
		</bndbox>
	</object>
	<object>
		<name>person</name>
		<pose>Unspecified</pose>
		<truncated>0</truncated>
		<difficult>0</difficult>
		<occluded>0</occluded>
		<bndbox>
			<xmin>320</xmin>
			<xmax>426</xmax>
			<ymin>183</ymin>
			<ymax>578</ymax>
		</bndbox>
	</object>
	<object>
		<name>person</name>
		<pose>Unspecified</pose>
		<truncated>0</truncated>
		<difficult>0</difficult>
		<occluded>0</occluded>
		<bndbox>
			<xmin>438</xmin>
			<xmax>527</xmax>
			<ymin>204</ymin>
			<ymax>635</ymax>
		</bndbox>
	</object>
	<object>
		<name>person</name>
		<pose>Unspecified</pose>
		<truncated>0</truncated>
		<difficult>0</difficult>
		<occluded>0</occluded>
		<bndbox>
			<xmin>162</xmin>
			<xmax>278</xmax>
			<ymin>228</ymin>
			<ymax>637</ymax>
		</bndbox>
	</object>
</annotation>
