<annotation>
	<folder></folder>
	<filename>ppe_1183_jpg.rf.a5e98028a3b8398fd2b71bc85eb66ac7.jpg</filename>
	<path>ppe_1183_jpg.rf.a5e98028a3b8398fd2b71bc85eb66ac7.jpg</path>
	<source>
		<database>roboflow.ai</database>
	</source>
	<size>
		<width>640</width>
		<height>640</height>
		<depth>3</depth>
	</size>
	<segmented>0</segmented>
	<object>
		<name>yellow</name>
		<pose>Unspecified</pose>
		<truncated>0</truncated>
		<difficult>0</difficult>
		<occluded>0</occluded>
		<bndbox>
			<xmin>230</xmin>
			<xmax>422</xmax>
			<ymin>239</ymin>
			<ymax>312</ymax>
		</bndbox>
	</object>
	<object>
		<name>person</name>
		<pose>Unspecified</pose>
		<truncated>0</truncated>
		<difficult>0</difficult>
		<occluded>0</occluded>
		<bndbox>
			<xmin>170</xmin>
			<xmax>581</xmax>
			<ymin>230</ymin>
			<ymax>623</ymax>
		</bndbox>
	</object>
</annotation>
