<annotation>
	<folder>Helmet_Head</folder>
	<filename>000422.jpg</filename>
	<path>PICTURE_DATA/Train</path>
	<source>
		<database>Unknown</database>
	</source>
	<size>
		<width>335</width>
		<height>501</height>
		<depth>3</depth>
	</size>
	<segmented>0</segmented>
	<object>
		<name>helmet</name>
		<pose>Unspecified</pose>
		<truncated>0</truncated>
		<difficult>0</difficult>
		<bndbox>
			<xmin>75</xmin>
			<ymin>217</ymin>
			<xmax>109</xmax>
			<ymax>253</ymax>
		</bndbox>
	</object>
</annotation>
