<annotation>
	<folder>Helmet_Head</folder>
	<filename>000790.jpg</filename>
	<path>PICTURE_DATA/Train</path>
	<source>
		<database>Unknown</database>
	</source>
	<size>
		<width>500</width>
		<height>333</height>
		<depth>3</depth>
	</size>
	<segmented>0</segmented>
	<object>
		<name>helmet</name>
		<pose>Unspecified</pose>
		<truncated>0</truncated>
		<difficult>0</difficult>
		<bndbox>
			<xmin>274</xmin>
			<ymin>134</ymin>
			<xmax>313</xmax>
			<ymax>178</ymax>
		</bndbox>
	</object>
	<object>
		<name>helmet</name>
		<pose>Unspecified</pose>
		<truncated>0</truncated>
		<difficult>0</difficult>
		<bndbox>
			<xmin>121</xmin>
			<ymin>155</ymin>
			<xmax>171</xmax>
			<ymax>207</ymax>
		</bndbox>
	</object>
	<object>
		<name>helmet</name>
		<pose>Unspecified</pose>
		<truncated>0</truncated>
		<difficult>0</difficult>
		<bndbox>
			<xmin>449</xmin>
			<ymin>143</ymin>
			<xmax>466</xmax>
			<ymax>158</ymax>
		</bndbox>
	</object>
	<object>
		<name>helmet</name>
		<pose>Unspecified</pose>
		<truncated>0</truncated>
		<difficult>0</difficult>
		<bndbox>
			<xmin>390</xmin>
			<ymin>138</ymin>
			<xmax>407</xmax>
			<ymax>155</ymax>
		</bndbox>
	</object>
</annotation>
