<annotation>
	<folder>Helmet_Head</folder>
	<filename>001386.jpg</filename>
	<path>PICTURE_DATA/Train</path>
	<source>
<database>NEU-MMLab</database>	</source>
	<size>
<width>533</width>
<height>300</height>
		<depth>3</depth>
	</size>
	<segmented>0</segmented>
	<object>
		<name>head</name>
		<pose>Unspecified</pose>
		<truncated>0</truncated>
		<difficult>0</difficult>
		<bndbox>
			<xmin>53</xmin>
			<ymin>100</ymin>
			<xmax>100</xmax>
			<ymax>142</ymax>
		</bndbox>
	</object>
	<object>
		<name>head</name>
		<pose>Unspecified</pose>
		<truncated>0</truncated>
		<difficult>0</difficult>
		<bndbox>
			<xmin>185</xmin>
			<ymin>83</ymin>
			<xmax>229</xmax>
			<ymax>138</ymax>
		</bndbox>
	</object>
	<object>
		<name>head</name>
		<pose>Unspecified</pose>
		<truncated>0</truncated>
		<difficult>0</difficult>
		<bndbox>
			<xmin>294</xmin>
			<ymin>75</ymin>
			<xmax>336</xmax>
			<ymax>129</ymax>
		</bndbox>
	</object>
	<object>
		<name>head</name>
		<pose>Unspecified</pose>
		<truncated>0</truncated>
		<difficult>0</difficult>
		<bndbox>
			<xmin>423</xmin>
			<ymin>74</ymin>
			<xmax>484</xmax>
			<ymax>146</ymax>
		</bndbox>
	</object>
</annotation>