<annotation>
	<folder>Helmet_Head</folder>
	<filename>001680.jpg</filename>
	<path>PICTURE_DATA/Train</path>
	<source>
		<database>Unknown</database>
	</source>
	<size>
		<width>534</width>
		<height>300</height>
		<depth>3</depth>
	</size>
	<segmented>0</segmented>
	<object>
		<name>helmet</name>
		<pose>Unspecified</pose>
		<truncated>0</truncated>
		<difficult>0</difficult>
		<bndbox>
			<xmin>272</xmin>
			<ymin>135</ymin>
			<xmax>292</xmax>
			<ymax>158</ymax>
		</bndbox>
	</object>
	<object>
		<name>helmet</name>
		<pose>Unspecified</pose>
		<truncated>0</truncated>
		<difficult>0</difficult>
		<bndbox>
			<xmin>295</xmin>
			<ymin>140</ymin>
			<xmax>323</xmax>
			<ymax>164</ymax>
		</bndbox>
	</object>
	<object>
		<name>helmet</name>
		<pose>Unspecified</pose>
		<truncated>0</truncated>
		<difficult>0</difficult>
		<bndbox>
			<xmin>342</xmin>
			<ymin>137</ymin>
			<xmax>364</xmax>
			<ymax>156</ymax>
		</bndbox>
	</object>
	<object>
		<name>helmet</name>
		<pose>Unspecified</pose>
		<truncated>0</truncated>
		<difficult>0</difficult>
		<bndbox>
			<xmin>391</xmin>
			<ymin>119</ymin>
			<xmax>412</xmax>
			<ymax>145</ymax>
		</bndbox>
	</object>
	<object>
		<name>helmet</name>
		<pose>Unspecified</pose>
		<truncated>0</truncated>
		<difficult>0</difficult>
		<bndbox>
			<xmin>405</xmin>
			<ymin>136</ymin>
			<xmax>424</xmax>
			<ymax>156</ymax>
		</bndbox>
	</object>
</annotation>
