<annotation>
	<folder>Helmet_Head</folder>
	<filename>003342.jpg</filename>
	<path>PICTURE_DATA/Train</path>
	<source>
<database>NEU-MMLab</database>	</source>
	<size>
<width>410</width>
<height>500</height>
		<depth>3</depth>
	</size>
	<segmented>0</segmented>
	<object>
		<name>helmet</name>
		<pose>Unspecified</pose>
		<truncated>0</truncated>
		<difficult>0</difficult>
		<bndbox>
			<xmin>137</xmin>
			<ymin>186</ymin>
			<xmax>243</xmax>
			<ymax>317</ymax>
		</bndbox>
	</object>
	<object>
		<name>helmet</name>
		<pose>Unspecified</pose>
		<truncated>0</truncated>
		<difficult>0</difficult>
		<bndbox>
			<xmin>52</xmin>
			<ymin>111</ymin>
			<xmax>120</xmax>
			<ymax>176</ymax>
		</bndbox>
	</object>
</annotation>