<annotation>
	<folder>Helmet_Head</folder>
	<filename>004207.jpg</filename>
	<path>PICTURE_DATA/Train</path>
	<source>
		<database>Unknown</database>
	</source>
	<size>
		<width>309</width>
		<height>448</height>
		<depth>3</depth>
	</size>
	<segmented>0</segmented>
	<object>
		<name>helmet</name>
		<pose>Unspecified</pose>
		<truncated>0</truncated>
		<difficult>0</difficult>
		<bndbox>
			<xmin>249</xmin>
			<ymin>253</ymin>
			<xmax>296</xmax>
			<ymax>305</ymax>
		</bndbox>
	</object>
	<object>
		<name>helmet</name>
		<pose>Unspecified</pose>
		<truncated>0</truncated>
		<difficult>0</difficult>
		<bndbox>
			<xmin>159</xmin>
			<ymin>235</ymin>
			<xmax>205</xmax>
			<ymax>289</ymax>
		</bndbox>
	</object>
	<object>
		<name>helmet</name>
		<pose>Unspecified</pose>
		<truncated>0</truncated>
		<difficult>0</difficult>
		<bndbox>
			<xmin>164</xmin>
			<ymin>182</ymin>
			<xmax>204</xmax>
			<ymax>235</ymax>
		</bndbox>
	</object>
	<object>
		<name>person</name>
		<pose>Unspecified</pose>
		<truncated>1</truncated>
		<difficult>0</difficult>
		<bndbox>
			<xmin>122</xmin>
			<ymin>240</ymin>
			<xmax>215</xmax>
			<ymax>448</ymax>
		</bndbox>
	</object>
	<object>
		<name>person</name>
		<pose>Unspecified</pose>
		<truncated>1</truncated>
		<difficult>0</difficult>
		<bndbox>
			<xmin>247</xmin>
			<ymin>254</ymin>
			<xmax>309</xmax>
			<ymax>445</ymax>
		</bndbox>
	</object>
	<object>
		<name>person</name>
		<pose>Unspecified</pose>
		<truncated>0</truncated>
		<difficult>0</difficult>
		<bndbox>
			<xmin>126</xmin>
			<ymin>185</ymin>
			<xmax>205</xmax>
			<ymax>243</ymax>
		</bndbox>
	</object>
</annotation>
